tagny_mcp_server/__init__.py
tagny_mcp_server/__main__.py
tagny_mcp_server/__version__.py
tagny_mcp_server/config.py
tagny_mcp_server/web_access/__init__.py
tagny_mcp_server/web_access/url_text_fetcher.py
tagny_mcp_server/web_access/web_search.py
tagny_mcp_server-1.0.2.dist-info/licenses/LICENSE
tagny_mcp_server-1.0.2.dist-info/METADATA
tagny_mcp_server-1.0.2.dist-info/WHEEL
tagny_mcp_server-1.0.2.dist-info/entry_points.txt
tagny_mcp_server-1.0.2.dist-info/top_level.txt
tagny_mcp_server-1.0.2.dist-info/RECORD
