Metadata-Version: 2.4
Name: tagny-mcp-server
Version: 1.0.2
Summary: An MCP server with web search, URL text fetching, and more tools to enhance locally served LLMs
Author-email: tagny ngompe <tagny@ymail.com>
License: MIT
Project-URL: Homepage, https://github.com/tagny/tagny-mcp-server
Project-URL: Repository, https://github.com/tagny/tagny-mcp-server
Project-URL: Bug Tracker, https://github.com/tagny/tagny-mcp-server/issues
Classifier: Programming Language :: Python :: 3
Classifier: License :: OSI Approved :: MIT License
Classifier: Operating System :: OS Independent
Requires-Python: <3.12,>=3.10
License-File: LICENSE
Requires-Dist: beautifulsoup4>=4.13.4
Requires-Dist: ddgs>=9.5.2
Requires-Dist: fastmcp>=2.11.3
Requires-Dist: requests>=2.32.4
Requires-Dist: typer>=0.16.0
Dynamic: license-file
